README.rst
setup.py
django_rayo_express.egg-info/PKG-INFO
django_rayo_express.egg-info/SOURCES.txt
django_rayo_express.egg-info/dependency_links.txt
django_rayo_express.egg-info/requires.txt
django_rayo_express.egg-info/top_level.txt
rayo_express/connector.py
rayo_express/handler.py
rayo_express/settings.py