Metadata-Version: 2.1
Name: django-rayo-express
Version: 1.0.0
Summary: Django Rayo Express Integration
Home-page: https://gitlab.com/linets/ecommerce/oms/integrations/django-rayo/
Author: Linets Development Team
Author-email: dteam@linets.cl
License: MIT
Platform: UNKNOWN
Requires-Python: >=3.7
